grpcalchemy/__init__.py
grpcalchemy/blueprint.py
grpcalchemy/config.py
grpcalchemy/meta.py
grpcalchemy/orm.py
grpcalchemy/server.py
grpcalchemy/types.py
grpcalchemy/utils.py
grpcalchemy/templates/README.md.tmpl
grpcalchemy/templates/rpc.proto.tmpl
grpcalchemy-0.7.3.dist-info/AUTHORS.rst
grpcalchemy-0.7.3.dist-info/LICENSE
grpcalchemy-0.7.3.dist-info/METADATA
grpcalchemy-0.7.3.dist-info/WHEEL
grpcalchemy-0.7.3.dist-info/top_level.txt
grpcalchemy-0.7.3.dist-info/RECORD
