Metadata-Version: 2.1
Name: grpcalchemy
Version: 0.7.3
Summary: The Python micro framework for building gPRC application.
Home-page: https://github.com/GuangTianLi/grpcalchemy
Author: GuangTian Li
Author-email: guangtian_li@qq.com
License: MIT license
Keywords: grpcalchemy
Platform: UNKNOWN
Classifier: Development Status :: 4 - Beta
Classifier: Intended Audience :: Developers
Classifier: License :: OSI Approved :: MIT License
Classifier: Natural Language :: English
Classifier: Programming Language :: Python :: 3
Classifier: Programming Language :: Python :: 3.6
Classifier: Programming Language :: Python :: 3.7
Classifier: Programming Language :: Python :: 3.8
Classifier: Programming Language :: Python :: 3.9
Requires-Python: >=3.6.0
Requires-Dist: grpcio (>=1.29.0)
Requires-Dist: protobuf
Requires-Dist: grpcio-tools (>=1.29.0)
Requires-Dist: jinja2
Requires-Dist: configalchemy
Requires-Dist: grpcio-reflection
Requires-Dist: grpcio-health-checking
